{
  "applications": [
    {
      "id": "0100d0902359c000"
    }
  ],
  "catch_copy": "成為靈能力嬰兒",
  "cloud_backup_type": "supported",
  "consumables": [],
  "content_type": "title",
  "copyright_text": "Skybound, Skybound Games and any related logos are registered or otherwise protected trademarks of Skybound, LLC. All rights reserved.",
  "courses": [],
  "demos": [],
  "description": "你扮演六個月大的嬰兒「艾薩克」，發展出神秘的靈能力。你最想要的是被家人關愛與接受，但神秘的科技企業卻想利用你。",
  "ex_membership_free": false,
  "features": [],
  "formal_name": "晚安宇宙（Goodnight Universe）",
  "genre": "冒險",
  "has_aoc": false,
  "hero_banner_url": "https://img-eshop.cdn.nintendo.net/i/0b56539df08d14311d3f6a1ff6ef9cfb03f7ea71a73d73bb81be0a784db51b30.jpg",
  "id": 70010000097209,
  "in_app_purchase": false,
  "included_bundles": [],
  "included_pretickets": [],
  "included_pt_right_ids": [],
  "is_new": false,
  "is_special_trial": false,
  "languages": [
    {
      "iso_code": "ja",
      "name": "日文"
    },
    {
      "iso_code": "en",
      "name": "英文"
    },
    {
      "iso_code": "pt",
      "name": "葡萄牙文"
    },
    {
      "iso_code": "es",
      "name": "西班牙文"
    },
    {
      "iso_code": "fr",
      "name": "法文"
    },
    {
      "iso_code": "de",
      "name": "德文"
    },
    {
      "iso_code": "zh",
      "name": "中文 (簡體字)"
    },
    {
      "iso_code": "zh",
      "name": "中文 (繁體字)"
    }
  ],
  "label_platform": "HAC",
  "membership_required": false,
  "movies": [],
  "notices": [],
  "platform": {
    "id": 2001,
    "name": "Nintendo Switch"
  },
  "play_styles": [
    {
      "id": 60,
      "name": "TV_MODE"
    },
    {
      "id": 61,
      "name": "TABLETOP_MODE"
    },
    {
      "id": 62,
      "name": "HANDHELD_MODE"
    }
  ],
  "player_number": {
    "offline_max": 1,
    "offline_min": 1
  },
  "public_status": "public",
  "publisher": {
    "id": 2109,
    "name": "Skybound Games"
  },
  "rating_info": {
    "content_descriptors": [],
    "rating": {
      "age": 0,
      "id": 1,
      "image_url": "https://img-eshop.cdn.nintendo.net/i/c962bd76d8db9462f11987a91dfecc2ae9acb80fab2ad5a87cd8b9e4b4f0c50a.jpg",
      "name": "NONE",
      "provisional": false,
      "svg_image_url": "https://img-eshop.cdn.nintendo.net/i/7609b5063d44d35347b700c192cb8b1c138c1678f6a885391a1928800990a4cc.svg"
    },
    "rating_system": {
      "id": 214,
      "name": "HK"
    }
  },
  "release_date_on_eshop": "2025-12-18",
  "rom_size_infos": [
    {
      "platform": "HAC",
      "total_rom_size": 3891265536
    },
    {
      "platform": "BEE",
      "total_rom_size": 3891265536
    }
  ],
  "screenshots": [
    {
      "images": [
        {
          "url": "https://img-eshop.cdn.nintendo.net/i/5e5a703822d48a0f9a9621495ab26cbddc3e87b1e3319c42bca837c8ff7dec2b.jpg"
        }
      ]
    },
    {
      "images": [
        {
          "url": "https://img-eshop.cdn.nintendo.net/i/2b0e282c5e920f3b0ccf28e50001a42857f20d7e8d7164fae1ed313f187ca6f8.jpg"
        }
      ]
    },
    {
      "images": [
        {
          "url": "https://img-eshop.cdn.nintendo.net/i/7591fe366da79ac7b480500dbfa69bd7afa4a7d2eaaba9d5cc11dfd56a8ce42f.jpg"
        }
      ]
    },
    {
      "images": [
        {
          "url": "https://img-eshop.cdn.nintendo.net/i/c21dc8ac82e6577d8d5e5340216b625a55a1b10f25c8b58609b77f5bce9b12ad.jpg"
        }
      ]
    }
  ],
  "target_titles": [],
  "rights": [
    {
      "title_id": "0100d0902359c000",
      "new_key021": true,
      "new_key022": true
    }
  ],
  "tags": [
    {
      "sub_category": {
        "name": "模擬",
        "category_id": "1"
      }
    },
    {
      "sub_category": {
        "name": "ELEMENT",
        "category_id": "2"
      }
    },
    {
      "sub_category": {
        "name": "冒險",
        "category_id": "1"
      }
    }
  ],
  "dominant_colors": [
    "050817",
    "b6edfe",
    "b69b58"
  ],
  "supported_features": {
    "game_share_online": false,
    "game_share_local": false,
    "game_chat_link": false
  }
}