{
	"Regions": {
		"True": [
			"GB",
			"DE",
			"FR",
			"IT",
			"BG",
			"CH",
			"CY",
			"EE",
			"HR",
			"IE",
			"LT",
			"LU",
			"LV",
			"MT",
			"RO",
			"SI",
			"SK",
			"AT",
			"BE",
			"CZ",
			"DK",
			"ES",
			"FI",
			"GR",
			"HU",
			"NL",
			"NO",
			"PL",
			"PT",
			"ZA",
			"SE"
		],
		"False": []
	},
	"name": [
		"Lethal League Blaze",
		"Lethal League Blaze",
		"Lethal League Blaze",
		"Lethal League Blaze",
		"Lethal League Blaze",
		"Lethal League Blaze",
		"Lethal League Blaze",
		"Lethal League Blaze",
		"Lethal League Blaze",
		"Lethal League Blaze",
		"Lethal League Blaze",
		"Lethal League Blaze",
		"Lethal League Blaze",
		"Lethal League Blaze",
		"Lethal League Blaze",
		"Lethal League Blaze",
		"Lethal League Blaze",
		"Lethal League Blaze",
		"Lethal League Blaze",
		"Lethal League Blaze",
		"Lethal League Blaze",
		"Lethal League Blaze",
		"Lethal League Blaze",
		"Lethal League Blaze",
		"Lethal League Blaze",
		"Lethal League Blaze",
		"Lethal League Blaze",
		"Lethal League Blaze",
		"Lethal League Blaze",
		"Lethal League Blaze",
		"Lethal League Blaze"
	],
	"publisher": [
		"Team Reptile"
	],
	"bannerUrl": [
		"https://www.nintendo.com/eu/media/images/10_share_images/games_15/nintendo_switch_download_software_1/H2x1_NSwitchDS_LethalLeagueBlaze.jpg"
	],
	"iconUrl": "",
	"releaseDate": [
		"12/07/2019"
	],
	"size": [
		"1.2 GiB"
	],
	"screenshots": []
}