{
  "applications": [
    {
      "id": "01009b2025f82000"
    }
  ],
  "catch_copy": "Experience every detail!",
  "cloud_backup_type": "supported",
  "consumables": [],
  "content_type": "title",
  "copyright_text": "© 17Studio LLC.",
  "courses": [],
  "demos": [],
  "description": "Complete captivating puzzles featuring realistic images of beautiful women. With each completed image, you'll unlock new images, and the gradually increasing difficulty will make completing the puzzle an engaging challenge. Intuitive touch controls create the feeling of actually touching every piece.\n\nSoft and relaxing music helps you immerse yourself in the atmosphere, and after completing the puzzle, you can carefully examine the image and admire every detail.\n\nFeatures:\n\n• Convenient one-handed play.\n• Realistic images of women.\n• Full immersion thanks to touch controls.\n• Gradual increase in level difficulty.\n• Atmospheric soundtrack.\n• Examine the picture after completing it.",
  "ex_membership_free": false,
  "features": [],
  "formal_name": "Hentai Gallery: Sexy Souls",
  "genre": "Puzzle / Simulation / Strategy / Party",
  "has_aoc": false,
  "hero_banner_url": "https://img-eshop.cdn.nintendo.net/i/6e55c9a996788341f13b8cee04ace88e3b3757d4017b9887461d2d959fa5b009.jpg",
  "id": 70010000111097,
  "in_app_purchase": false,
  "included_bundles": [],
  "included_pretickets": [],
  "included_pt_right_ids": [],
  "is_new": true,
  "is_special_trial": false,
  "languages": [
    {
      "iso_code": "ja",
      "name": "Japanese"
    },
    {
      "iso_code": "en",
      "name": "English"
    },
    {
      "iso_code": "ru",
      "name": "Russian"
    }
  ],
  "label_platform": "HAC",
  "membership_required": false,
  "movies": [],
  "network_feature_description": "This software supports the following:\n- Touch screen",
  "notices": [],
  "platform": {
    "id": 2001,
    "name": "Nintendo Switch"
  },
  "play_styles": [
    {
      "id": 60,
      "name": "TV_MODE"
    },
    {
      "id": 61,
      "name": "TABLETOP_MODE"
    },
    {
      "id": 62,
      "name": "HANDHELD_MODE"
    }
  ],
  "player_number": {
    "offline_max": 1,
    "offline_min": 1
  },
  "public_status": "public",
  "publisher": {
    "id": 3953,
    "name": "17Studio"
  },
  "rating_info": {
    "content_descriptors": [
      {
        "id": 80,
        "name": "Sexualised Imagery",
        "type": "descriptor"
      }
    ],
    "rating": {
      "age": 15,
      "id": 4,
      "image_url": "https://img-eshop.cdn.nintendo.net/i/0b8c70559b2f83ad8e741e29af202e92974cf0026788195d32e75b5e1a59a7aa.jpg",
      "name": "MA15+",
      "provisional": false,
      "svg_image_url": "https://img-eshop.cdn.nintendo.net/i/d73b42fc6556de53790e79ef84327570cd855f1853417f91a11d4f3eaf321b82.svg"
    },
    "rating_system": {
      "id": 308,
      "name": "COB"
    }
  },
  "release_date_on_eshop": "2026-01-01",
  "rom_size_infos": [
    {
      "platform": "HAC",
      "total_rom_size": 216006656,
      "estimated_rom_size": 210763776
    },
    {
      "platform": "BEE",
      "total_rom_size": 216006656
    }
  ],
  "screenshots": [
    {
      "images": [
        {
          "url": "https://img-eshop.cdn.nintendo.net/i/01514cb6cf7a2c84c7bc70772de333d4e2e7dc5137b0502539ec3cb345d667e0.jpg"
        }
      ]
    },
    {
      "images": [
        {
          "url": "https://img-eshop.cdn.nintendo.net/i/d27981f6b9f8e89c3add822cc8a722c8d66f100eb020fce4d16de4d9277c8d4a.jpg"
        }
      ]
    },
    {
      "images": [
        {
          "url": "https://img-eshop.cdn.nintendo.net/i/1c04c1b76707ec7270a6f3e9b52bd42a2bb04ed60e393637b0c09253064c2ff2.jpg"
        }
      ]
    }
  ],
  "target_titles": [],
  "rights": [
    {
      "title_id": "01009b2025f82000",
      "new_key021": true,
      "new_key022": true
    }
  ],
  "tags": [
    {
      "sub_category": {
        "name": "Puzzle",
        "category_id": "1"
      }
    }
  ],
  "dominant_colors": [
    "f7f9fa",
    "544a2d",
    "c6344e"
  ],
  "supported_features": {
    "game_share_online": false,
    "game_share_local": false,
    "game_chat_link": false
  }
}